{
  "scanned_at": 1784611235.4253297,
  "results": [
    {
      "coin": "LDO",
      "return": 0.13636363636363646
    },
    {
      "coin": "ADA",
      "return": 0.08064516129032251
    },
    {
      "coin": "MINA",
      "return": 0.08009153318077789
    },
    {
      "coin": "UNI",
      "return": 0.07960199004975133
    },
    {
      "coin": "WLD",
      "return": 0.07812937552506316
    },
    {
      "coin": "NEAR",
      "return": 0.062434417628541405
    },
    {
      "coin": "BCH",
      "return": 0.058901389808074134
    },
    {
      "coin": "ROSE",
      "return": 0.05492424242424243
    },
    {
      "coin": "SNX",
      "return": 0.052863436123347984
    },
    {
      "coin": "LINK",
      "return": 0.05155384244760319
    },
    {
      "coin": "APT",
      "return": 0.048124678883370464
    },
    {
      "coin": "ARB",
      "return": 0.047729918509895164
    },
    {
      "coin": "INJ",
      "return": 0.04691794267766003
    },
    {
      "coin": "FIL",
      "return": 0.04674220963172804
    },
    {
      "coin": "ZRX",
      "return": 0.044452750114537753
    },
    {
      "coin": "DOT",
      "return": 0.0435323383084576
    },
    {
      "coin": "XTZ",
      "return": 0.04280510018214945
    },
    {
      "coin": "XRP",
      "return": 0.042043149548220526
    },
    {
      "coin": "BAT",
      "return": 0.041649979975971085
    },
    {
      "coin": "CRV",
      "return": 0.04134615384615392
    },
    {
      "coin": "CHZ",
      "return": 0.041095890410958846
    },
    {
      "coin": "ETH",
      "return": 0.03979978354978342
    },
    {
      "coin": "SUI",
      "return": 0.038508309687879994
    },
    {
      "coin": "ENS",
      "return": 0.03846153846153855
    },
    {
      "coin": "RENDER",
      "return": 0.03731343283582089
    },
    {
      "coin": "SOL",
      "return": 0.03387587667063663
    },
    {
      "coin": "SEI",
      "return": 0.0332014072119613
    },
    {
      "coin": "AAVE",
      "return": 0.03234441222395734
    },
    {
      "coin": "ZEC",
      "return": 0.031340915101824685
    },
    {
      "coin": "ATOM",
      "return": 0.030949105914718222
    },
    {
      "coin": "GRT",
      "return": 0.030864197530864335
    },
    {
      "coin": "FET",
      "return": 0.029644268774703608
    },
    {
      "coin": "STX",
      "return": 0.0295930949445129
    },
    {
      "coin": "ETC",
      "return": 0.02798232695139924
    },
    {
      "coin": "MANA",
      "return": 0.027900146842878337
    },
    {
      "coin": "SAND",
      "return": 0.027896995708154515
    },
    {
      "coin": "COMP",
      "return": 0.026946107784431073
    },
    {
      "coin": "XLM",
      "return": 0.025638106390822424
    },
    {
      "coin": "BTC",
      "return": 0.025153326775272378
    },
    {
      "coin": "AVAX",
      "return": 0.023183925811437467
    },
    {
      "coin": "ALGO",
      "return": 0.022004889975550057
    },
    {
      "coin": "OP",
      "return": 0.021505376344086002
    },
    {
      "coin": "DOGE",
      "return": 0.020061728395061706
    },
    {
      "coin": "AXS",
      "return": 0.018619934282584794
    },
    {
      "coin": "FLOW",
      "return": 0.015127388535031816
    },
    {
      "coin": "TIA",
      "return": 0.01431779898933172
    },
    {
      "coin": "LTC",
      "return": 0.010904425914047389
    },
    {
      "coin": "DASH",
      "return": 0.01038267576386831
    },
    {
      "coin": "YFI",
      "return": 0.009569332612550996
    },
    {
      "coin": "IMX",
      "return": 0.0
    },
    {
      "coin": "EGLD",
      "return": -0.012618296529968487
    },
    {
      "coin": "SKL",
      "return": -0.025000000000000022
    }
  ]
}