{
  "scanned_at": 1784685640.469578,
  "results": [
    {
      "coin": "AAVE",
      "return": 0.04528750540423698
    },
    {
      "coin": "FIL",
      "return": 0.04037685060565277
    },
    {
      "coin": "IMX",
      "return": 0.038523274478330594
    },
    {
      "coin": "COMP",
      "return": 0.02953337271116352
    },
    {
      "coin": "BAT",
      "return": 0.026729760838982042
    },
    {
      "coin": "XLM",
      "return": 0.023810029523587017
    },
    {
      "coin": "OP",
      "return": 0.02083333333333326
    },
    {
      "coin": "DOT",
      "return": 0.017899761336515496
    },
    {
      "coin": "DASH",
      "return": 0.017590149516270914
    },
    {
      "coin": "XRP",
      "return": 0.017175402687550134
    },
    {
      "coin": "BTC",
      "return": 0.01289011330644474
    },
    {
      "coin": "DOGE",
      "return": 0.011546391752577323
    },
    {
      "coin": "FLOW",
      "return": 0.010184097140618853
    },
    {
      "coin": "ADA",
      "return": 0.009860788863109038
    },
    {
      "coin": "FET",
      "return": 0.008968609865470878
    },
    {
      "coin": "LINK",
      "return": 0.007529248233522745
    },
    {
      "coin": "APT",
      "return": 0.006599571027883222
    },
    {
      "coin": "GRT",
      "return": 0.0059880239520957446
    },
    {
      "coin": "AXS",
      "return": 0.005370569280343629
    },
    {
      "coin": "YFI",
      "return": 0.005337736105704094
    },
    {
      "coin": "ALGO",
      "return": 0.004778972520907976
    },
    {
      "coin": "MINA",
      "return": 0.004282655246252709
    },
    {
      "coin": "BCH",
      "return": 0.004250559284116218
    },
    {
      "coin": "TIA",
      "return": 0.003594138789051682
    },
    {
      "coin": "EGLD",
      "return": 0.0031847133757960666
    },
    {
      "coin": "ETC",
      "return": 0.0028612303290413976
    },
    {
      "coin": "ETH",
      "return": 0.0028356860178866405
    },
    {
      "coin": "SOL",
      "return": 0.0015357051446123204
    },
    {
      "coin": "SAND",
      "return": 0.0
    },
    {
      "coin": "CHZ",
      "return": 0.0
    },
    {
      "coin": "SKL",
      "return": 0.0
    },
    {
      "coin": "SUI",
      "return": -0.00013015749056355386
    },
    {
      "coin": "STX",
      "return": -0.0005980861244018199
    },
    {
      "coin": "CRV",
      "return": -0.0009259259259259967
    },
    {
      "coin": "SEI",
      "return": -0.0017068487305312852
    },
    {
      "coin": "UNI",
      "return": -0.0021574973031284195
    },
    {
      "coin": "XTZ",
      "return": -0.005242463958060162
    },
    {
      "coin": "INJ",
      "return": -0.005572065378900537
    },
    {
      "coin": "RENDER",
      "return": -0.005859375000000111
    },
    {
      "coin": "ARB",
      "return": -0.0066225165562914245
    },
    {
      "coin": "ROSE",
      "return": -0.007194244604316613
    },
    {
      "coin": "WLD",
      "return": -0.007526602647287772
    },
    {
      "coin": "ATOM",
      "return": -0.009314703925482282
    },
    {
      "coin": "LTC",
      "return": -0.009940778341793521
    },
    {
      "coin": "AVAX",
      "return": -0.010542168674698704
    },
    {
      "coin": "MANA",
      "return": -0.015514809590973289
    },
    {
      "coin": "ENS",
      "return": -0.017241379310344862
    },
    {
      "coin": "SNX",
      "return": -0.02127659574468077
    },
    {
      "coin": "ZRX",
      "return": -0.02638470904454493
    },
    {
      "coin": "LDO",
      "return": -0.032418952618453845
    },
    {
      "coin": "ZEC",
      "return": -0.036683745775645815
    },
    {
      "coin": "NEAR",
      "return": -0.04100790513833985
    }
  ]
}