{
  "scanned_at": 1784317725.4515822,
  "results": [
    {
      "coin": "ENS",
      "return": 0.07226107226107215
    },
    {
      "coin": "ADA",
      "return": 0.020923076923076822
    },
    {
      "coin": "DASH",
      "return": 0.016617210682492445
    },
    {
      "coin": "INJ",
      "return": 0.016436159551012297
    },
    {
      "coin": "ZEC",
      "return": 0.012672064027270835
    },
    {
      "coin": "XTZ",
      "return": 0.005850585058505775
    },
    {
      "coin": "MANA",
      "return": 0.005555555555555758
    },
    {
      "coin": "APT",
      "return": 0.005389514943655138
    },
    {
      "coin": "FET",
      "return": 0.0037712130735387817
    },
    {
      "coin": "ETC",
      "return": 0.0028571428571428914
    },
    {
      "coin": "LDO",
      "return": 0.0027100271002709064
    },
    {
      "coin": "DOT",
      "return": 0.00235017626321965
    },
    {
      "coin": "SAND",
      "return": 0.0020790020790022457
    },
    {
      "coin": "LTC",
      "return": 0.001776198934280604
    },
    {
      "coin": "BAT",
      "return": 0.0015048908954100604
    },
    {
      "coin": "STX",
      "return": 0.0012055455093429313
    },
    {
      "coin": "BTC",
      "return": 0.0009312021890510724
    },
    {
      "coin": "ARB",
      "return": -0.0011123470522801382
    },
    {
      "coin": "AVAX",
      "return": -0.0015174506828528056
    },
    {
      "coin": "ZRX",
      "return": -0.0015705709898088394
    },
    {
      "coin": "ROSE",
      "return": -0.0017574692442881013
    },
    {
      "coin": "EGLD",
      "return": -0.003154574132492094
    },
    {
      "coin": "COMP",
      "return": -0.0034843205574912606
    },
    {
      "coin": "ALGO",
      "return": -0.0036101083032490378
    },
    {
      "coin": "DOGE",
      "return": -0.005478701547733333
    },
    {
      "coin": "GRT",
      "return": -0.005747126436781547
    },
    {
      "coin": "XRP",
      "return": -0.006017505470459428
    },
    {
      "coin": "SOL",
      "return": -0.00779186476492344
    },
    {
      "coin": "BCH",
      "return": -0.008966387311886148
    },
    {
      "coin": "ATOM",
      "return": -0.010450685826257411
    },
    {
      "coin": "SUI",
      "return": -0.010452961672473893
    },
    {
      "coin": "RENDER",
      "return": -0.01072386058981234
    },
    {
      "coin": "SEI",
      "return": -0.011569204880101047
    },
    {
      "coin": "FLOW",
      "return": -0.012561857632280238
    },
    {
      "coin": "SNX",
      "return": -0.013274336283185861
    },
    {
      "coin": "ETH",
      "return": -0.014427730332992827
    },
    {
      "coin": "XLM",
      "return": -0.015481017323995538
    },
    {
      "coin": "FIL",
      "return": -0.016731016731016735
    },
    {
      "coin": "AAVE",
      "return": -0.019076522870149604
    },
    {
      "coin": "LINK",
      "return": -0.01927194860813719
    },
    {
      "coin": "MINA",
      "return": -0.02145922746781115
    },
    {
      "coin": "SKL",
      "return": -0.023809523809523614
    },
    {
      "coin": "YFI",
      "return": -0.02546892454673344
    },
    {
      "coin": "UNI",
      "return": -0.026960110041265417
    },
    {
      "coin": "OP",
      "return": -0.030000000000000027
    },
    {
      "coin": "WLD",
      "return": -0.03109201213346824
    },
    {
      "coin": "CRV",
      "return": -0.031616982836495056
    },
    {
      "coin": "IMX",
      "return": -0.03981968444778361
    },
    {
      "coin": "CHZ",
      "return": -0.04166666666666663
    },
    {
      "coin": "AXS",
      "return": -0.049695740365111485
    },
    {
      "coin": "NEAR",
      "return": -0.0498273310310805
    },
    {
      "coin": "TIA",
      "return": -0.06953561876975445
    }
  ]
}